vectorGC/__init__.py
vectorGC-0.1.2.dist-info/LICENSE
vectorGC-0.1.2.dist-info/METADATA
vectorGC-0.1.2.dist-info/WHEEL
vectorGC-0.1.2.dist-info/top_level.txt
vectorGC-0.1.2.dist-info/RECORD
