Metadata-Version: 2.1
Name: vectorGC
Version: 0.1.2
Summary: Implementation of the Vector-GC method and its regression framework
Author: Carl Hemprich
Author-email: chemprich@ethz.ch
Classifier: Programming Language :: Python :: 3
Classifier: License :: OSI Approved :: MIT License
License-File: LICENSE
Requires-Dist: rdkit >=2023.3.3
Requires-Dist: numpy >=1.26.0
Requires-Dist: pandas >=2.0.3
Requires-Dist: torch >=2.1.0
Requires-Dist: feos >=0.4.3
Requires-Dist: feos-torch >=0.1.0
Requires-Dist: scipy >=1.11.4
Requires-Dist: tqdm >=4.66.1
